LICENSE
MANIFEST.in
README.md
setup.py
docs/0001soccer.jpeg
docs/0001soccer.jpeg.predictions.png
docs/rot45_skeleton_wholebody.png
docs/skeleton_wholebody.png
openpifpaf_wholebody/__init__.py
openpifpaf_wholebody/constants.py
openpifpaf_wholebody/wholebody_metrics.py
openpifpaf_wholebody/wholebodykp.py
openpifpaf_wholebody.egg-info/PKG-INFO
openpifpaf_wholebody.egg-info/SOURCES.txt
openpifpaf_wholebody.egg-info/dependency_links.txt
openpifpaf_wholebody.egg-info/requires.txt
openpifpaf_wholebody.egg-info/top_level.txt
openpifpaf_wholebody/helper_scripts/Get_annotations_from_coco_wholebody.py
openpifpaf_wholebody/helper_scripts/Visualize_annotations.py