Metadata-Version: 2.1
Name: openpifpaf-wholebody
Version: 0.1.0
Summary: OpenPifPaf wholebody Extension
Home-page: https://github.com/vita-epfl/openpifpaf_wholebody
Author: Duncan Zauss
License: GNU AGPLv3
Platform: UNKNOWN
